PyNCBI/Constants.py
PyNCBI/FileUtilities.py
PyNCBI/GEOReader.py
PyNCBI/GSE.py
PyNCBI/GSM.py
PyNCBI/Utilities.py
PyNCBI/__init__.py
PyNCBI/_types.py
PyNCBI/config.py
PyNCBI/exceptions.py
PyNCBI/logging.py
PyNCBI/py.typed
PyNCBI/core/__init__.py
PyNCBI/core/protocols.py
PyNCBI/io/__init__.py
PyNCBI/io/cache.py
PyNCBI/io/compression.py
PyNCBI/io/http_client.py
PyNCBI/parsing/__init__.py
PyNCBI/parsing/soft_parser.py
PyNCBI/services/__init__.py
PyNCBI/services/gse_service.py
PyNCBI/services/gsm_service.py
pyncbi-0.2.0.dist-info/licenses/LICENSE
pyncbi-0.2.0.dist-info/METADATA
pyncbi-0.2.0.dist-info/WHEEL
pyncbi-0.2.0.dist-info/top_level.txt
pyncbi-0.2.0.dist-info/RECORD
