Metadata-Version: 2.4
Name: PyNCBI
Version: 0.2.0
Summary: Simple API for Python Integration with NCBI GEO Database
Author-email: Thomas Konstantinovsky <thomaskon90@gmail.com>
License: MIT
Project-URL: Homepage, https://github.com/MuteJester/PyNCBI
Project-URL: Documentation, https://pyncbi.readthedocs.io/
Project-URL: Repository, https://github.com/MuteJester/PyNCBI
Project-URL: Issues, https://github.com/MuteJester/PyNCBI/issues
Project-URL: Changelog, https://github.com/MuteJester/PyNCBI/releases
Keywords: api,database,analytics,biology,methylation,epigenetics,ncbi,geo,bioinformatics
Classifier: Development Status :: 4 - Beta
Classifier: Intended Audience :: Developers
Classifier: Intended Audience :: Science/Research
Classifier: Topic :: Scientific/Engineering :: Bio-Informatics
Classifier: Topic :: Scientific/Engineering :: Information Analysis
Classifier: License :: OSI Approved :: MIT License
Classifier: Operating System :: OS Independent
Classifier: Programming Language :: Python :: 3
Classifier: Programming Language :: Python :: 3.11
Classifier: Programming Language :: Python :: 3.12
Classifier: Programming Language :: Python :: 3.13
Classifier: Typing :: Typed
Requires-Python: >=3.11
License-File: LICENSE
Requires-Dist: methylprep>=1.7.0
Requires-Dist: wget>=3.2
Requires-Dist: tqdm>=4.66.0
Requires-Dist: pandas>=2.0.0
Requires-Dist: numpy<3.0.0,>=1.26.0
Requires-Dist: requests>=2.31.0
Requires-Dist: termcolor>=2.4.0
Provides-Extra: dev
Requires-Dist: pytest>=8.0.0; extra == "dev"
Requires-Dist: pytest-cov>=4.1.0; extra == "dev"
Requires-Dist: ruff>=0.4.0; extra == "dev"
Requires-Dist: mypy>=1.10.0; extra == "dev"
Requires-Dist: pandas-stubs>=2.0.0; extra == "dev"
Requires-Dist: types-requests>=2.31.0; extra == "dev"
Requires-Dist: types-tqdm>=4.66.0; extra == "dev"
Provides-Extra: docs
Requires-Dist: sphinx>=7.0.0; extra == "docs"
Requires-Dist: sphinx-rtd-theme>=2.0.0; extra == "docs"
Requires-Dist: sphinx-autodoc-typehints>=2.0.0; extra == "docs"
Dynamic: license-file
